{
    "version": "b2967",
    "description": "Port of Facebook's LLaMA model in C/C++",
    "homepage": "https://github.com/ggerganov/llama.cpp",
    "license": "MIT",
    "notes": "Default URL is http://localhost:8080",
    "url": "https://github.com/ggerganov/llama.cpp/releases/download/b2967/llama-b2967-bin-win-avx2-x64.zip",
    "hash": "7f8f10696d00b930609b746033ca358f6f46a8073b594e3e3e2e42f1ca0bf675",
    "bin": [
        [
            "server.exe",
            "llama-cpp-avx2-server"
        ]
    ],
    "checkver": {
        "url": "https://github.com/ggerganov/llama.cpp/releases",
        "regex": "tag/(.{5})"
    },
    "autoupdate": {
        "url": "https://github.com/ggerganov/llama.cpp/releases/download/$version/llama-$version-bin-win-avx2-x64.zip"
    }
}
