{
    "version": "b2282",
    "description": "Port of Facebook's LLaMA model in C/C++",
    "homepage": "https://github.com/ggerganov/llama.cpp",
    "license": "MIT",
    "notes": "Default URL is http://localhost:8080",
    "url": "https://github.com/ggerganov/llama.cpp/releases/download/b2282/llama-b2282-bin-win-avx2-x64.zip",
    "hash": "ea4c29af3e3bc3a2856045df35ed5c03c9f0f681544412ce526517314947af97",
    "bin": [
        [
            "server.exe",
            "llama-cpp-avx2-server"
        ]
    ],
    "checkver": {
        "url": "https://github.com/ggerganov/llama.cpp/releases",
        "regex": "tag/(.{5})"
    },
    "autoupdate": {
        "url": "https://github.com/ggerganov/llama.cpp/releases/download/$version/llama-$version-bin-win-avx2-x64.zip"
    }
}
