{
    "version": "master-81844fb",
    "description": "Port of Facebook's LLaMA model in C/C++",
    "homepage": "https://github.com/ggerganov/llama.cpp",
    "license": "MIT",
    "notes": "Default URL is http://localhost:8080",
    "url": "https://github.com/ggerganov/llama.cpp/releases/download/master-81844fb/llama-master-81844fb-bin-win-avx2-x64.zip",
    "hash": "9881d13b434fe3e389b2c8b552f3c4df8a6c6c1adea00a6e63b601a156d7bf37",
    "bin": [
        [
            "server.exe",
            "llama-cpp-avx2-server"
        ]
    ],
    "checkver": {
        "url": "https://github.com/ggerganov/llama.cpp/releases",
        "regex": "tag/(master-.{7})"
    },
    "autoupdate": {
        "url": "https://github.com/ggerganov/llama.cpp/releases/download/$version/llama-$version-bin-win-avx2-x64.zip"
    }
}
