{
    "version": "b2497",
    "description": "Port of Facebook's LLaMA model in C/C++",
    "homepage": "https://github.com/ggerganov/llama.cpp",
    "license": "MIT",
    "notes": "Default URL is http://localhost:8080",
    "url": "https://github.com/ggerganov/llama.cpp/releases/download/b2497/llama-b2497-bin-win-avx2-x64.zip",
    "hash": "e83a22142405f140294b017020456963f1b9b77e0613bd57e496cbb600cabe33",
    "bin": [
        [
            "server.exe",
            "llama-cpp-avx2-server"
        ]
    ],
    "checkver": {
        "url": "https://github.com/ggerganov/llama.cpp/releases",
        "regex": "tag/(.{5})"
    },
    "autoupdate": {
        "url": "https://github.com/ggerganov/llama.cpp/releases/download/$version/llama-$version-bin-win-avx2-x64.zip"
    }
}
