{
    "version": "b2034",
    "description": "Port of Facebook's LLaMA model in C/C++",
    "homepage": "https://github.com/ggerganov/llama.cpp",
    "license": "MIT",
    "notes": "Default URL is http://localhost:8080",
    "url": "https://github.com/ggerganov/llama.cpp/releases/download/b2034/llama-b2034-bin-win-avx2-x64.zip",
    "hash": "27d87e30419f3c5b8ef4d85ea5c7f19177e0fda71c3d4263672fcb4e1d411837",
    "bin": [
        [
            "server.exe",
            "llama-cpp-avx2-server"
        ]
    ],
    "checkver": {
        "url": "https://github.com/ggerganov/llama.cpp/releases",
        "regex": "tag/(.{5})"
    },
    "autoupdate": {
        "url": "https://github.com/ggerganov/llama.cpp/releases/download/$version/llama-$version-bin-win-avx2-x64.zip"
    }
}
